nimbbl/__init__.py
nimbbl/client.py
nimbbl/errors.py
nimbbl/constants/__init__.py
nimbbl/constants/error_code.py
nimbbl/constants/http_status_code.py
nimbbl/constants/url.py
nimbbl/resources/__init__.py
nimbbl/resources/base.py
nimbbl/resources/order.py
nimbbl/resources/segment.py
nimbbl/resources/transaction.py
nimbbl/resources/user.py
nimbbl/utility/__init__.py
nimbbl/utility/utility.py
tests/__init__.py
tests/helpers.py
tests/test_client_order.py
tests/test_client_transaction.py
tests/test_client_user.py
tests/testutil.py
nimbbl_python_sdk-0.0.3.dist-info/LICENSE
nimbbl_python_sdk-0.0.3.dist-info/METADATA
nimbbl_python_sdk-0.0.3.dist-info/WHEEL
nimbbl_python_sdk-0.0.3.dist-info/top_level.txt
nimbbl_python_sdk-0.0.3.dist-info/RECORD
