Metadata-Version: 2.1
Name: nimbbl-python-sdk
Version: 0.0.3
Summary: Nimbbl SDK for python
Home-page: https://github.com/nimbbl-tech/nimbbl-python-sdk
Author: Rakshit
Author-email: rakshit@nimbbl.biz
License: UNKNOWN
Project-URL: Bug Tracker, https://github.com/nimbbl-tech/nimbbl-python-sdk/issues
Platform: UNKNOWN
Classifier: Programming Language :: Python :: 3
Classifier: License :: OSI Approved :: MIT License
Classifier: Operating System :: OS Independent
Requires-Python: >=3.6
License-File: LICENSE
